{"Le Seigneur des anneaux": {"production_year": 1978, "title_french": "Le Seigneur des anneaux", "user_rating": 3.6584384, "directors": ["Ralph Bakshi"], "actors": ["John Hurt", "Dominic Guard", "Christopher Guard", "William Squire", "Simon Chandler"], "allocine_id": 38512}, "La Bande \u00e0 Picsou : le film - Le Tr\u00e9sor de la lampe perdue": {"production_year": 1990, "title_french": "La Bande \u00e0 Picsou : le film - Le Tr\u00e9sor de la lampe perdue", "user_rating": 3.258136, "directors": ["Bob Hathcock", "Paul Brizzi", "Ga\u00ebttan Brizzi"], "actors": ["Richard Libertini", "Russi Taylor", "Alan Young", "Terence McGovern", "Christopher Lloyd"], "allocine_id": 47120}, "Storks": {"production_year": 2016, "directors": ["Doug Sweetland", "Nicholas Stoller"], "actors": ["Kelsey Grammer", "Andy Samberg"], "title_french": "Storks", "allocine_id": 237409}, "Batman: Under the Red Hood": {"production_year": 2010, "user_rating": 4.1866255, "title_french": "Batman: Under the Red Hood", "allocine_id": 183831}, "Invitation \u00e0 la danse": {"production_year": 1956, "title_french": "Invitation \u00e0 la danse", "user_rating": 3.2200956, "directors": ["Gene Kelly"], "actors": ["Gene Kelly", "Claire Sombert", "Diana Adams", "Tamara Toumanova", "Igor Youskevitch"], "allocine_id": 20642}, "Merlin l'enchanteur": {"production_year": 1963, "title_french": "Merlin l'enchanteur", "user_rating": 3.9839501, "directors": ["Wolfgang Reitherman"], "actors": ["Rickie Sorensen", "Karl Swenson", "Sebastian Cabot", "Junius Matthews", "Martha Wentworth"], "allocine_id": 45518}, "Pok\u00e9mon 2, le pouvoir est en toi": {"production_year": 1999, "title_french": "Pok\u00e9mon 2, le pouvoir est en toi", "user_rating": 2.5218868, "directors": ["Kunihiko Yuyama", "Michael Haigney"], "actors": ["Eric Stuart", "Ted Lewis", "Rachael Lillis", "Veronica Taylor", "Addie Blaustein"], "allocine_id": 27477}, "La Grande Aventure Lego": {"production_year": 2014, "title_french": "La Grande Aventure Lego", "user_rating": 3.9846828, "directors": ["Christopher Miller", "Phil Lord"], "actors": ["Will Ferrell", "Morgan Freeman", "Chris Pratt", "Elizabeth Banks", "Will Arnett"], "allocine_id": 171198}, "Appleseed Ex Machina": {"production_year": 2007, "user_rating": 3.653479, "directors": ["Shinji Aramaki"], "title_french": "Appleseed Ex Machina", "allocine_id": 61662}, "The Lego Batman Movie": {"production_year": 2017, "directors": ["Chris McKay"], "actors": ["Zach Galifianakis", "Rosario Dawson", "Michael Cera", "Will Arnett"], "title_french": "The Lego Batman Movie", "allocine_id": 232239}, "Scooby-Doo! rencontre avec KISS": {"production_year": 2015, "title_french": "Scooby-Doo! rencontre avec KISS", "user_rating": 2.7583334, "directors": ["Tony Cervone", "Spike Brandt"], "actors": ["Matthew Lillard", "Frank Welker", "Gene Simmons", "Eric Singer", "Mindy Cohn"], "allocine_id": 239326}, "South Park, le film": {"production_year": 1998, "title_french": "South Park, le film", "user_rating": 3.309814, "directors": ["Trey Parker"], "actors": ["George Clooney", "Trey Parker", "Matt Stone", "Isaac Hayes", "Mary Kay Bergman"], "allocine_id": 20395}, "Cendrillon 2: Une vie de princesse (V)": {"production_year": 2002, "title_french": "Cendrillon 2: Une vie de princesse (V)", "user_rating": 2.4295247, "directors": ["John Kafka"], "actors": ["Jennifer Hale", "Tress MacNeille", "Corey Burton", "Holland Taylor", "Rob Paulsen"], "allocine_id": 126607}, "Excalibur, l'\u00e9p\u00e9e magique": {"production_year": 1998, "title_french": "Excalibur, l'\u00e9p\u00e9e magique", "user_rating": 3.6173809, "directors": ["Frederik Du Chau"], "actors": ["Bryan White", "Jessalyn Gilsig", "Gary Oldman", "Cary Elwes", "Andrea Corr"], "allocine_id": 29767}, "Batman: Year One": {"production_year": 2011, "title_french": "Batman: Year One", "user_rating": 4.0761557, "directors": ["Sam Liu", "Lauren Montgomery"], "actors": ["Katee Sackhoff", "Bryan Cranston", "Ben McKenzie", "Alex Rocco", "Eliza Dushku"], "allocine_id": 182689}, "The Charlie Brown and Snoopy Show": {"user_rating": 2.8448367, "title_french": "The Charlie Brown and Snoopy Show", "allocine_id": 5564}, "Le P\u00f4le Express": {"production_year": 2004, "title_french": "Le P\u00f4le Express", "user_rating": 3.150122, "directors": ["Robert Zemeckis"], "actors": ["Eddie Deezen", "Tom Hanks", "Leslie Harter Zemeckis", "Josh Hutcherson", "Nona Gaye"], "allocine_id": 29144}, "The Prodigies": {"production_year": 2010, "title_french": "The Prodigies", "user_rating": 3.1088865, "directors": ["Antoine Charreyron"], "actors": ["Isabelle Van Waes", "Jacob Rosenbaum", "Dominic Gould", "Moon Dailly Monira", "Jeffrey Evan Thomas"], "allocine_id": 136215}, "Le Roi et moi": {"production_year": 1999, "title_french": "Le Roi et moi", "user_rating": 2.8425925, "directors": ["Richard Rich"], "actors": ["David Burnham", "Miranda Richardson", "Martin Vidnovic", "Ian Richardson", "Darrell Hammond"], "allocine_id": 19993}, "La L\u00e9gende de Beowulf": {"production_year": 2007, "title_french": "La L\u00e9gende de Beowulf", "user_rating": 2.492015, "directors": ["Robert Zemeckis"], "actors": ["Angelina Jolie Pitt", "Ray Winstone", "Robin Wright", "Anthony Hopkins", "Crispin Glover"], "allocine_id": 59408}, "Animatrix": {"production_year": 2003, "title_french": "Animatrix", "user_rating": 3.4550269, "directors": ["Mahiro Maeda", "Shinichir\u00f4 Watanabe", "Yoshiaki Kawajiri", "Koji Morimoto", "Takeshi Koike"], "actors": ["Clayton Watson", "Pamela Adlon", "Hedy Burress", "Terrence \"T.C.\" Carson", "Akio Ohtsuka"], "allocine_id": 49543}, "Max & Co": {"production_year": 2007, "title_french": "Max & Co", "user_rating": 2.7512615, "directors": ["Samuel Guillaume", "Frederic Guillaume"], "actors": ["Denis Podalyd\u00e8s", "Lor\u00e0nt Deutsch", "Virginie Efira", "Sanseverino", "Patrick Bouchitey"], "allocine_id": 125323}, "Les Noces fun\u00e8bres": {"production_year": 2004, "title_french": "Les Noces fun\u00e8bres", "user_rating": 3.9776747, "directors": ["Mike Johnson", "Tim Burton"], "actors": ["Paul Whitehouse", "Johnny Depp", "Tracey Ullman", "Emily Watson", "Helena Bonham Carter"], "allocine_id": 56718}, "La Petite Sir\u00e8ne": {"production_year": 1990, "title_french": "La Petite Sir\u00e8ne", "user_rating": 3.7117662, "directors": ["Ron Clements", "John Musker"], "actors": ["Claire Guyot", "Thierry Ragueneau", "Pat Carroll", "Christopher Daniel Barnes", "Jodi Benson"], "allocine_id": 18115}, "Bernard et Bianca au pays des kangourous": {"production_year": 1990, "title_french": "Bernard et Bianca au pays des kangourous", "user_rating": 3.2050014, "directors": ["Hendel Butoy", "Mike Gabriel"], "actors": ["Adam Ryen", "Tristan Rogers", "John Candy", "Eva Gabor", "Bob Newhart"], "allocine_id": 32049}, "Happy Feet": {"production_year": 2005, "title_french": "Happy Feet", "user_rating": 3.0437882, "directors": ["George Miller"], "actors": ["Marion Cotillard", "Sophie Marceau", "Elijah Wood", "Anthony Kavanagh", "Kad Merad"], "allocine_id": 52416}, "Le G\u00e9ant de fer": {"production_year": 1999, "title_french": "Le G\u00e9ant de fer", "user_rating": 3.8043046, "directors": ["Brad Bird"], "actors": ["Cloris Leachman", "Harry Connick Jr", "Jennifer Aniston", "Vin Diesel", "Eli Marienthal"], "allocine_id": 21709}, "Oliver et compagnie": {"production_year": 1988, "title_french": "Oliver et compagnie", "user_rating": 3.3553944, "directors": ["George Scribner"], "actors": ["Billy Joel", "Richard Mulligan", "Roscoe Lee Browne", "Cheech Marin", "Joseph Lawrence"], "allocine_id": 5178}, "Le Royaume de Ga'Hoole - la l\u00e9gende des gardiens": {"production_year": 2010, "title_french": "Le Royaume de Ga'Hoole - la l\u00e9gende des gardiens", "user_rating": 3.7507353, "directors": ["Zack Snyder"], "actors": ["Adrienne DeFaria", "Jim Sturgess", "Emily Barclay", "Abbie Cornish", "Essie Davis"], "allocine_id": 135561}, "Star Wars: The Clone Wars": {"production_year": 2008, "title_french": "Star Wars: The Clone Wars", "user_rating": 3.2033753, "directors": ["Dave Filoni"], "actors": ["Samuel L. Jackson", "Anthony Daniels", "Matt Lanter", "Christopher Lee", "Ashley Eckstein"], "allocine_id": 136230}, "Lucas, fourmi malgr\u00e9 lui": {"production_year": 2005, "title_french": "Lucas, fourmi malgr\u00e9 lui", "user_rating": 2.4056294, "directors": ["John A. Davis"], "actors": ["Nicolas Cage", "Meryl Streep", "Julia Roberts", "Zach Tyler", "Bruce Campbell"], "allocine_id": 40139}, "Qui veut la peau de Roger Rabbit ?": {"production_year": 1988, "title_french": "Qui veut la peau de Roger Rabbit ?", "user_rating": 3.9820418, "directors": ["Robert Zemeckis"], "actors": ["Charles Fleischer", "Joanna Cassidy", "Kathleen Turner", "Bob Hoskins", "Christopher Lloyd"], "allocine_id": 4066}, "Pok\u00e9mon : Le Sort des Zarbi": {"production_year": 2001, "title_french": "Pok\u00e9mon : Le Sort des Zarbi", "user_rating": 2.8237195, "directors": ["Kunihiko Yuyama", "Michael Haigney"], "actors": ["Ikue Ootani", "Addie Blaustein", "Rachael Lillis", "Veronica Taylor", "Eric Stuart"], "allocine_id": 29307}, "Les Looney Tunes passent \u00e0 l'action": {"production_year": 2002, "title_french": "Les Looney Tunes passent \u00e0 l'action", "user_rating": 2.2058117, "directors": ["Joe Dante"], "actors": ["Heather Locklear", "Brendan Fraser", "Steve Martin", "Timothy Dalton", "Jenna Elfman"], "allocine_id": 45043}, "Lego DC Comics Super Heroes: Justice League vs. Bizarro League": {"production_year": 2015, "title_french": "Lego DC Comics Super Heroes: Justice League vs. Bizarro League", "user_rating": 2.781075, "directors": ["Brandon Vietti"], "actors": ["Nolan North", "Diedrich Bader", "Troy Baker", "Khary Payton", "Grey Delisle"], "allocine_id": 233054}, "Osmosis Jones": {"production_year": 2001, "title_french": "Osmosis Jones", "user_rating": 3.281946, "directors": ["Bobby Farrelly", "Peter Farrelly"], "actors": ["Brandy Norwood", "Molly Shannon", "Bill Murray", "Chris Rock", "Chris Elliott"], "allocine_id": 29278}, "Comme chiens et chats": {"production_year": 2001, "title_french": "Comme chiens et chats", "user_rating": 2.0509639, "directors": ["Lawrence Guterman"], "actors": ["Alec Baldwin", "Alexander Pollock", "Tobey Maguire", "Elizabeth Perkins", "Jeff Goldblum"], "allocine_id": 29294}, "Scooby-Doo! le fant\u00f4me de l'op\u00e9ra": {"production_year": 2013, "title_french": "Scooby-Doo! le fant\u00f4me de l'op\u00e9ra", "user_rating": 3.1696832, "directors": ["Victor Cook"], "actors": ["Matthew Lillard", "Frank Welker", "Isabella Acres", "Mindy Cohn", "Troy Baker"], "allocine_id": 223542}, "A Scanner Darkly": {"production_year": 2006, "title_french": "A Scanner Darkly", "user_rating": 3.2457354, "directors": ["Richard Linklater"], "actors": ["Rory Cochrane", "Woody Harrelson", "Winona Ryder", "Keanu Reeves", "Robert Downey Jr."], "allocine_id": 56561}, "Les Supers Nanas - Powerpuff girls, le film": {"production_year": 2001, "title_french": "Les Supers Nanas - Powerpuff girls, le film", "user_rating": 3.1663373, "directors": ["Craig McCracken"], "actors": ["Cathy Cavadini", "Tara Strong", "Tom Kenny", "Roger L. Jackson", "Elizabeth Daily"], "allocine_id": 43356}, "Ninjago": {"user_rating": 3.0394547, "actors": ["Ian James Corlett", "John Novak", "Jillian Michaels"], "title_french": "Ninjago", "allocine_id": 12204}, "Happy Feet 2": {"production_year": 2011, "title_french": "Happy Feet 2", "user_rating": 3.1810591, "directors": ["George Miller"], "actors": ["Carlos Alazraqui", "Pink", "Robin Williams", "Ava Acres", "Sofia Vergara"], "allocine_id": 140675}, "Les Chimpanz\u00e9s de l'espace": {"production_year": 2008, "title_french": "Les Chimpanz\u00e9s de l'espace", "user_rating": 1.8966548, "directors": ["Kirk De Micco"], "actors": [" Patrick Warburton", " Jeff Daniels", " Cheryl Hines", " Kristin Chenoweth", "Andy Samberg"], "allocine_id": 131693}, "Batman : L'Alliance des h\u00e9ros": {"user_rating": 2.683023, "actors": ["Diedrich Bader"], "title_french": "Batman : L'Alliance des h\u00e9ros", "allocine_id": 5233}, "Mewtwo contre-attaque": {"production_year": 1998, "title_french": "Mewtwo contre-attaque", "user_rating": 2.3432071, "directors": ["Kunihiko Yuyama", "Michael Haigney"], "actors": ["Eric Stuart", "Philip Bartlett", "Rachael Lillis", "Veronica Taylor", "Ikue Ootani"], "allocine_id": 23497}, "TMNT les tortues ninja": {"production_year": 2007, "title_french": "TMNT les tortues ninja", "user_rating": 2.0198689, "directors": ["Kevin Munroe"], "actors": ["Nolan North", "James Arnold Taylor", "Mikey Kelley", "Mitchell Whitfield", "Chris Evans"], "allocine_id": 61615}, "Yu-gi-oh ! The Movie": {"production_year": 2004, "title_french": "Yu-gi-oh ! The Movie", "user_rating": 2.8467615, "directors": ["Tsuji Hatsuki"], "actors": ["Dan Green", "Frank Frankson", "Amy Birnbaum", "Wayne Grayson", "Eric Stuart"], "allocine_id": 56717}, "Yogi l'ours": {"production_year": 2008, "title_french": "Yogi l'ours", "user_rating": 2.319171, "directors": ["Eric Brevig"], "actors": ["Justin Timberlake", "Dan Aykroyd", "T.J. Miller", "Anna Faris", "Tom Cavanagh"], "allocine_id": 144132}}